tqsdk/__init__.py
tqsdk/__version__.py
tqsdk/api.py
tqsdk/auth.py
tqsdk/baseApi.py
tqsdk/baseModule.py
tqsdk/calendar.py
tqsdk/changelog_notification.py
tqsdk/channel.py
tqsdk/connect.py
tqsdk/constants.py
tqsdk/data_extension.py
tqsdk/data_series.py
tqsdk/datetime.py
tqsdk/datetime_state.py
tqsdk/diff.py
tqsdk/entity.py
tqsdk/exceptions.py
tqsdk/expired_quotes.json.lzma
tqsdk/ins_schema.py
tqsdk/log.py
tqsdk/multiaccount.py
tqsdk/objs.py
tqsdk/objs_not_entity.py
tqsdk/rangeset.py
tqsdk/report.py
tqsdk/risk_manager.py
tqsdk/risk_rule.py
tqsdk/sm.py
tqsdk/stockprofit.py
tqsdk/symbols.py
tqsdk/ta.py
tqsdk/tafunc.py
tqsdk/tqwebhelper.py
tqsdk/trade_extension.py
tqsdk/trading_status.py
tqsdk/utils.py
tqsdk/utils_symbols.py
tqsdk/zq.py
tqsdk/zq_otg.py
tqsdk/__pyinstaller/__init__.py
tqsdk/__pyinstaller/hook-tqsdk.py
tqsdk/algorithm/__init__.py
tqsdk/algorithm/time_table_generater.py
tqsdk/algorithm/twap.py
tqsdk/backtest/__init__.py
tqsdk/backtest/backtest.py
tqsdk/backtest/replay.py
tqsdk/backtest/utils.py
tqsdk/demo/__init__.py
tqsdk/demo/download_orders.py
tqsdk/demo/multiaccount.py
tqsdk/demo/ta.py
tqsdk/demo/ta_option.py
tqsdk/demo/example/Aroon.py
tqsdk/demo/example/CCI.py
tqsdk/demo/example/CMO.py
tqsdk/demo/example/Keltner_Channel.py
tqsdk/demo/example/Qstick.py
tqsdk/demo/example/RSI.py
tqsdk/demo/example/TRIX.py
tqsdk/demo/example/__init__.py
tqsdk/demo/example/aberration.py
tqsdk/demo/example/crack_spread_arbitrage.py
tqsdk/demo/example/crush_spread.py
tqsdk/demo/example/cu-al-spread.py
tqsdk/demo/example/distance_based.py
tqsdk/demo/example/doublema.py
tqsdk/demo/example/dualthrust.py
tqsdk/demo/example/escalator.py
tqsdk/demo/example/fairy_four_price.py
tqsdk/demo/example/fractal-trend.py
tqsdk/demo/example/gridtrading.py
tqsdk/demo/example/gridtrading_async.py
tqsdk/demo/example/handicap_algorithm.py
tqsdk/demo/example/hull.py
tqsdk/demo/example/iceberg_algorithm.py
tqsdk/demo/example/jm-j-spread.py
tqsdk/demo/example/kalman_filter_pairs_trading.py
tqsdk-3.8.9.dist-info/LICENSE
tqsdk-3.8.9.dist-info/METADATA
tqsdk-3.8.9.dist-info/WHEEL
tqsdk-3.8.9.dist-info/entry_points.txt
tqsdk-3.8.9.dist-info/top_level.txt
tqsdk-3.8.9.dist-info/RECORD
