Metadata-Version: 2.1
Name: tqsdk
Version: 3.8.9
Summary: TianQin SDK
Home-page: https://www.shinnytech.com/tqsdk
Author: TianQin
Author-email: tianqincn@gmail.com
License: UNKNOWN
Platform: UNKNOWN
Classifier: Programming Language :: Python :: 3
Classifier: License :: OSI Approved :: Apache Software License
Classifier: Operating System :: OS Independent
Requires-Python: >=3.8
License-File: LICENSE
Requires-Dist: websockets (>=10.1)
Requires-Dist: requests
Requires-Dist: numpy
Requires-Dist: pandas (>=1.1.0)
Requires-Dist: scipy
Requires-Dist: simplejson
Requires-Dist: aiohttp
Requires-Dist: certifi
Requires-Dist: pyjwt
Requires-Dist: psutil (>=5.9.6)
Requires-Dist: shinny-structlog
Requires-Dist: sgqlc
Requires-Dist: filelock
Requires-Dist: tqsdk-ctpse
Requires-Dist: tqsdk-sm
Requires-Dist: packaging
